zenif/__init__.py
zenif/constants.py
zenif/utils.py
zenif/cli/__init__.py
zenif/cli/applets/__init__.py
zenif/cli/applets/commands.py
zenif/cli/applets/core.py
zenif/cli/applets/error_handlers.py
zenif/cli/applets/exceptions.py
zenif/cli/applets/help.py
zenif/cli/applets/installer.py
zenif/cli/applets/parameters.py
zenif/cli/applets/parser.py
zenif/cli/prompt/__init__.py
zenif/cli/prompt/base.py
zenif/cli/prompt/checkbox.py
zenif/cli/prompt/choice.py
zenif/cli/prompt/confirm.py
zenif/cli/prompt/date.py
zenif/cli/prompt/editor.py
zenif/cli/prompt/key.py
zenif/cli/prompt/number.py
zenif/cli/prompt/password.py
zenif/cli/prompt/prompt.py
zenif/cli/prompt/text.py
zenif/decorators/__init__.py
zenif/decorators/core.py
zenif/decorators/exceptions.py
zenif/log/__init__.py
zenif/log/core.py
zenif/log/handlers.py
zenif/log/template.py
zenif/schema/__init__.py
zenif/schema/core.py
zenif/schema/exceptions.py
zenif/schema/fields.py
zenif/schema/validators.py
zenif-0.5.2.dist-info/licenses/LICENSE
zenif-0.5.2.dist-info/METADATA
zenif-0.5.2.dist-info/WHEEL
zenif-0.5.2.dist-info/top_level.txt
zenif-0.5.2.dist-info/RECORD
