Metadata-Version: 2.4
Name: zenif
Version: 0.5.2
Summary: Various utilties to enhance your projects
Author: dombom
License: MIT License
Project-URL: GitHub, https://github.com/DomBom16/zenif
Keywords: utils,logger,log
Classifier: License :: OSI Approved :: MIT License
Classifier: Programming Language :: Python
Classifier: Programming Language :: Python :: 3
Requires-Python: >=3.12
License-File: LICENSE
Requires-Dist: black
Requires-Dist: pygments
Requires-Dist: colorama
Dynamic: license-file
